LICENSE
README.md
pyproject.toml
setup.py
./src/geoconv/preprocessing/c_extension/c_extension.c
src/geoconv/__init__.py
src/geoconv.egg-info/PKG-INFO
src/geoconv.egg-info/SOURCES.txt
src/geoconv.egg-info/dependency_links.txt
src/geoconv.egg-info/requires.txt
src/geoconv.egg-info/top_level.txt
src/geoconv/preprocessing/__init__.py
src/geoconv/preprocessing/barycentric_coordinates.py
src/geoconv/preprocessing/gpc_system.py
src/geoconv/preprocessing/gpc_system_group.py
src/geoconv/preprocessing/gpc_system_utils.py
src/geoconv/preprocessing/c_extension/__init__.py
src/geoconv/preprocessing/c_extension/c_extension.c
src/geoconv/pytorch/__init__.py
src/geoconv/pytorch/layers/__init__.py
src/geoconv/pytorch/layers/angular_avg_pooling.py
src/geoconv/pytorch/layers/angular_max_pooling.py
src/geoconv/pytorch/layers/angular_min_pooling.py
src/geoconv/pytorch/layers/conv_chi_squared.py
src/geoconv/pytorch/layers/conv_dirac.py
src/geoconv/pytorch/layers/conv_exp.py
src/geoconv/pytorch/layers/conv_geodesic.py
src/geoconv/pytorch/layers/conv_intrinsic.py
src/geoconv/pytorch/layers/conv_student_t.py
src/geoconv/pytorch/layers/conv_zero.py
src/geoconv/pytorch/models/__init__.py
src/geoconv/pytorch/models/resnet_block.py
src/geoconv/tensorflow/__init__.py
src/geoconv/tensorflow/layers/__init__.py
src/geoconv/tensorflow/layers/angular_avg_pooling.py
src/geoconv/tensorflow/layers/angular_max_pooling.py
src/geoconv/tensorflow/layers/angular_min_pooling.py
src/geoconv/tensorflow/layers/conv_chi_squared.py
src/geoconv/tensorflow/layers/conv_dirac.py
src/geoconv/tensorflow/layers/conv_exp.py
src/geoconv/tensorflow/layers/conv_geodesic.py
src/geoconv/tensorflow/layers/conv_intrinsic.py
src/geoconv/tensorflow/layers/conv_student_t.py
src/geoconv/tensorflow/layers/conv_zero.py
src/geoconv/tensorflow/models/__init__.py
src/geoconv/tensorflow/models/resnet_block.py
src/geoconv/utils/__init__.py
src/geoconv/utils/measures.py
src/geoconv/utils/misc.py
src/geoconv/utils/visualization.py
src/geoconv_examples/__init__.py
src/geoconv_examples/mpi_faust/__init__.py
src/geoconv_examples/mpi_faust/data/__init__.py
src/geoconv_examples/mpi_faust/data/preprocess_faust.py
