Metadata-Version: 2.4
Name: geoconv
Version: 0.0.8
Summary: Intrinsic Surface Convolutions for everyone!
Author: Andreas Mazur
Maintainer: Andreas Mazur
License-Expression: GPL-3.0-only
Project-URL: Repository, https://github.com/andreasMazur/geoconv
Project-URL: Issues, https://github.com/andreasMazur/geoconv/issues
Keywords: surface,surface-convolution,convolution,intrinsic-surface-convolution,machine-learning,deep-learning,neural-network,convolutional-neural-networks,deep-neural-network,tensorflow,keras,pytorch,geometry,geometry-processing,geodesic,geodesic-algorithm,geometric,geometric-deep-learning,visualization,benchmarking
Classifier: Development Status :: 4 - Beta
Classifier: Intended Audience :: Education
Classifier: Intended Audience :: Developers
Classifier: Intended Audience :: Science/Research
Classifier: Topic :: Education
Classifier: Topic :: Scientific/Engineering
Classifier: Topic :: Scientific/Engineering :: Artificial Intelligence
Classifier: Topic :: Scientific/Engineering :: Information Analysis
Classifier: Topic :: Scientific/Engineering :: Mathematics
Classifier: Topic :: Scientific/Engineering :: Physics
Classifier: Topic :: Scientific/Engineering :: Visualization
Classifier: Programming Language :: Python :: 3.10
Classifier: Programming Language :: Python :: 3.11
Requires-Python: >=3.10
License-File: LICENSE
Requires-Dist: numpy<=1.26.4,>=1.22.0
Requires-Dist: tqdm>=4.64.0
Requires-Dist: trimesh>=3.12.6
Requires-Dist: pyglet>=1.5.27
Requires-Dist: matplotlib>=3.5.2
Requires-Dist: open3d>=0.17.0
Requires-Dist: networkx>=2.8.6
Requires-Dist: pygeodesic>=0.1.7
Requires-Dist: Pillow>=10.0.1
Requires-Dist: scipy>=1.10.0
Requires-Dist: pyglet<2
Provides-Extra: pytorch
Requires-Dist: torch; extra == "pytorch"
Requires-Dist: torchvision; extra == "pytorch"
Requires-Dist: torchaudio; extra == "pytorch"
Requires-Dist: torcheval; extra == "pytorch"
Provides-Extra: tensorflow
Requires-Dist: tensorflow; extra == "tensorflow"
Provides-Extra: tensorflow-gpu
Requires-Dist: tensorflow[and-cuda]; extra == "tensorflow-gpu"
Dynamic: license-file
